owa/core/__init__.py
owa/core/auto_discovery.py
owa/core/callable.py
owa/core/component_access.py
owa/core/listener.py
owa/core/message.py
owa/core/messages.py
owa/core/plugin_discovery.py
owa/core/plugin_spec.py
owa/core/registry.py
owa/core/runnable.py
owa/core/time.py
owa/core/documentation/__init__.py
owa/core/documentation/validator.py
owa/core/io/__init__.py
owa/core/io/media.py
owa/core/io/video/__init__.py
owa/core/io/video/reader.py
owa/core/io/video/typing.py
owa/core/io/video/writer.py
owa/core/runner/__init__.py
owa/core/runner/subprocess_runner.py
owa/core/utils/__init__.py
owa/core/utils/backup.py
owa/core/utils/easydict.py
owa/core/utils/resource_cache.py
owa/core/utils/tempfile.py
owa/core/utils/typing.py
owa/env/plugins/std.py
owa/env/std/__init__.py
owa/env/std/clock.py
owa_core-0.6.5.dist-info/METADATA
owa_core-0.6.5.dist-info/WHEEL
owa_core-0.6.5.dist-info/entry_points.txt
owa_core-0.6.5.dist-info/RECORD
